keras_adamw/__init__.py
keras_adamw/optimizers.py
keras_adamw/optimizers_225.py
keras_adamw/optimizers_225tf.py
keras_adamw/optimizers_v2.py
keras_adamw/utils.py
keras_adamw-1.38.dist-info/LICENSE
keras_adamw-1.38.dist-info/METADATA
keras_adamw-1.38.dist-info/WHEEL
keras_adamw-1.38.dist-info/top_level.txt
keras_adamw-1.38.dist-info/zip-safe
keras_adamw-1.38.dist-info/RECORD
