Metadata-Version: 2.1
Name: keras-adamw
Version: 1.38
Summary: Keras implementation of AdamW, SGDW, NadamW, Warm Restarts, and Learning Rate multipliers
Home-page: https://github.com/OverLordGoldDragon/keras-adamw
Author: OverLordGoldDragon
Author-email: 16495490+OverLordGoldDragon@users.noreply.github.com
License: MIT
Keywords: tensorflow keras optimizers adamw adamwr nadam sgd learning-rate-multipliers warm-restarts
Platform: UNKNOWN
Classifier: Programming Language :: Python :: 3.6
Classifier: Programming Language :: Python :: 3.7
Classifier: Programming Language :: Python :: 3.8
Classifier: License :: OSI Approved :: MIT License
Classifier: Operating System :: OS Independent
Classifier: Intended Audience :: Developers
Classifier: Intended Audience :: Education
Classifier: Intended Audience :: Information Technology
Classifier: Intended Audience :: Science/Research
Classifier: Topic :: Utilities
Classifier: Topic :: Scientific/Engineering
Classifier: Topic :: Scientific/Engineering :: Artificial Intelligence
Classifier: Topic :: Scientific/Engineering :: Information Analysis
Classifier: Topic :: Software Development
Classifier: Topic :: Software Development :: Libraries :: Python Modules
